{
  "version-7.0.0-guides": {
    "Getting Started": [
      "version-7.0.0-guide-about",
      "version-7.0.0-guide-platform-support",
      "version-7.0.0-guide-installation"
    ],
    "Usage": [
      "version-7.0.0-guide-usage",
      "version-7.0.0-guide-cli",
      "version-7.0.0-guide-debugging",
      "version-7.0.0-guide-errors",
      "version-7.0.0-guide-testing"
    ],
    "API Core": [
      "version-7.0.0-api-serialport"
    ],
    "API Bindings": [
      "version-7.0.0-api-bindings",
      "version-7.0.0-api-binding-mock",
      "version-7.0.0-api-binding-abstract"
    ],
    "API Interfaces": [
      "version-7.0.0-api-stream"
    ],
    "API Parsers": [
      "version-7.0.0-api-parsers-overview",
      "version-7.0.0-api-parser-byte-length",
      "version-7.0.0-api-parser-cctalk",
      "version-7.0.0-api-parser-delimiter",
      "version-7.0.0-api-parser-inter-byte-timeout",
      "version-7.0.0-api-parser-readline",
      "version-7.0.0-api-parser-ready",
      "version-7.0.0-api-parser-regex",
      "version-7.0.0-api-parser-slip-encoder"
    ],
    "Community": [
      "version-7.0.0-code-of-conduct"
    ]
  }
}
